CHANGELOG.md
LICENSE
README.md
benchmark_parallel.py
build_nuitka.py
channel_generation.py
constants.py
get_version.py
gui.py
gui_main.py
hrir.py
impulcifer-cli.py
impulcifer.py
impulcifer_cli.py
impulse_response.py
impulse_response_estimator.py
localization.py
logger.py
microphone_deviation_correction.py
modern_gui.py
parallel_processing.py
parallel_utils.py
pyproject.toml
recorder.py
resource_helper.py
room_correction.py
test_build.py
test_integration.py
test_microphone_deviation.py
test_parallel_processing.py
test_suite.py
update_checker.py
updater.py
utils.py
data/11cmaster.mlp
data/13cmaster.mlp
data/harman-in-room-headphone-target-wo-bass.csv
data/harman-in-room-headphone-target.csv
data/harman-in-room-loudspeaker-target-wo-bass.csv
data/harman-in-room-loudspeaker-target.csv
data/sweep-6.15s-48000Hz-32bit-2.93Hz-24000Hz.pkl
data/sweep-6.15s-48000Hz-32bit-2.93Hz-24000Hz.wav
"data/sweep-seg-FL,FR-stereo-6.15s-48000Hz-32bit-2.93Hz-24000Hz.wav"
data/sweep-seg-FL-mono-6.15s-48000Hz-32bit-2.93Hz-24000Hz.wav
data/sweep-seg-FL-stereo-6.15s-48000Hz-32bit-2.93Hz-24000Hz.wav
data/sweep-seg-FR-stereo-6.15s-48000Hz-32bit-2.93Hz-24000Hz.wav
data/demo/README.md
data/demo/room-mic-calibration.txt
data/demo/room-target.csv
font/Pretendard-Regular.otf
img/audacity_amplify.png
img/audacity_settings.png
img/audacity_wav_export.png
img/headphones_recording.png
img/input_device.png
img/mics.jpg
img/output_device.png
img/speakers_recording.png
img/sweep_sequence.png
impulcifer_py313-2.1.5.data/data/impulcifer_py313/data/11cmaster.mlp
impulcifer_py313-2.1.5.data/data/impulcifer_py313/data/13cmaster.mlp
impulcifer_py313-2.1.5.data/data/impulcifer_py313/data/harman-in-room-headphone-target-wo-bass.csv
impulcifer_py313-2.1.5.data/data/impulcifer_py313/data/harman-in-room-headphone-target.csv
impulcifer_py313-2.1.5.data/data/impulcifer_py313/data/harman-in-room-loudspeaker-target-wo-bass.csv
impulcifer_py313-2.1.5.data/data/impulcifer_py313/data/harman-in-room-loudspeaker-target.csv
impulcifer_py313-2.1.5.dist-info/METADATA
impulcifer_py313-2.1.5.dist-info/WHEEL
impulcifer_py313-2.1.5.dist-info/entry_points.txt
impulcifer_py313-2.1.5.dist-info/licenses/LICENSE
impulcifer_py313-2.1.5.dist-info/RECORD
