Metadata-Version: 2.4
Name: impulcifer-py313
Version: 2.1.5
Summary: HRIR 측정 및 헤드폰 바이노럴 헤드트래킹 HRTF 시스템 (Python 3.14 Free-Threaded 지원)
Project-URL: Homepage, https://github.com/jaakkopasanen/impulcifer
Project-URL: Python 3.13.2 호환 버전, https://github.com/115dkk/Impulcifer-pip313
Author: 원본 저자: Jaakko Pasanen, Python 3.13/3.14 호환 버전: 115dkk
License-File: LICENSE
Classifier: License :: OSI Approved :: MIT License
Classifier: Operating System :: OS Independent
Classifier: Programming Language :: Python :: 3
Classifier: Programming Language :: Python :: 3.9
Classifier: Programming Language :: Python :: 3.10
Classifier: Programming Language :: Python :: 3.11
Classifier: Programming Language :: Python :: 3.12
Classifier: Programming Language :: Python :: 3.13
Classifier: Programming Language :: Python :: 3.14
Classifier: Topic :: Multimedia :: Sound/Audio
Classifier: Topic :: Scientific/Engineering
Requires-Python: <3.15,>=3.9
Requires-Dist: autoeq-py313>=1.2.0
Requires-Dist: bokeh>=3.0.0
Requires-Dist: customtkinter>=5.2.0
Requires-Dist: matplotlib>=3.8.0
Requires-Dist: nnresample>=0.2.4
Requires-Dist: numpy>=1.26.0
Requires-Dist: packaging>=23.0
Requires-Dist: scipy>=1.12.0
Requires-Dist: seaborn
Requires-Dist: sounddevice>=0.4.6
Requires-Dist: soundfile>=0.12.1
Requires-Dist: tabulate>=0.9.0
